gdaltools/__init__.py
gdaltools/api.py
gdaltools/basetypes.py
gdaltools/gdalinfocmd.py
gdaltools/gdalsrsinfo.py
gdaltools/metadata.py
gdaltools/ogr2ogrcmd.py
gdaltools/ogrinfocmd.py
pygdaltools-1.4.2.dist-info/LICENSE
pygdaltools-1.4.2.dist-info/METADATA
pygdaltools-1.4.2.dist-info/WHEEL
pygdaltools-1.4.2.dist-info/top_level.txt
pygdaltools-1.4.2.dist-info/RECORD
